Metadata-Version: 2.1
Name: my-get-config-prabhu
Version: 0.0.1
Summary: my_get_config
Home-page: UNKNOWN
License: UNKNOWN
Platform: UNKNOWN
